mm_base5/__init__.py
mm_base5/py.typed
mm_base5/core/__init__.py
mm_base5/core/config.py
mm_base5/core/core.py
mm_base5/core/db.py
mm_base5/core/dconfig.py
mm_base5/core/dvalue.py
mm_base5/core/errors.py
mm_base5/core/system_service.py
mm_base5/core/utils.py
mm_base5/server/__init__.py
mm_base5/server/auth.py
mm_base5/server/config.py
mm_base5/server/deps.py
mm_base5/server/jinja.py
mm_base5/server/server.py
mm_base5/server/utils.py
mm_base5/server/assets/base.css
mm_base5/server/assets/base.js
mm_base5/server/assets/pico.slate.min.css
mm_base5/server/assets/sortable.min.js
mm_base5/server/routers/__init__.py
mm_base5/server/routers/api_method_router.py
mm_base5/server/routers/auth_router.py
mm_base5/server/routers/dconfig_router.py
mm_base5/server/routers/dlog_router.py
mm_base5/server/routers/dvalue_router.py
mm_base5/server/routers/system_router.py
mm_base5/server/routers/ui_router.py
mm_base5/server/templates/dconfigs.j2
mm_base5/server/templates/dconfigs_multiline.j2
mm_base5/server/templates/dconfigs_toml.j2
mm_base5/server/templates/dlogs.j2
mm_base5/server/templates/dvalues.j2
mm_base5/server/templates/dvalues_update.j2
mm_base5/server/templates/login.j2
mm_base5/server/templates/system.j2
mm_base5/server/templates/inc/base.j2
mm_base5-0.0.9.dist-info/METADATA
mm_base5-0.0.9.dist-info/WHEEL
mm_base5-0.0.9.dist-info/RECORD
