Metadata-Version: 2.4
Name: mm-base5
Version: 0.0.9
Requires-Python: >=3.12
Requires-Dist: fastapi[standard]>=0.115.11
Requires-Dist: itsdangerous~=2.2.0
Requires-Dist: mm-jinja~=0.0.4
Requires-Dist: mm-mongo>=0.3.7
Requires-Dist: mm-telegram~=0.0.5
Requires-Dist: pydantic-settings>=2.8.0
